NiChartHarmonize/__init__.py
NiChartHarmonize/nh_apply_model.py
NiChartHarmonize/nh_cli.py
NiChartHarmonize/nh_learn_model.py
NiChartHarmonize/nh_utils.py
NiChartHarmonize-2.2.0.dist-info/LICENSE
NiChartHarmonize-2.2.0.dist-info/METADATA
NiChartHarmonize-2.2.0.dist-info/WHEEL
NiChartHarmonize-2.2.0.dist-info/entry_points.txt
NiChartHarmonize-2.2.0.dist-info/top_level.txt
NiChartHarmonize-2.2.0.dist-info/RECORD
