Metadata-Version: 2.1
Name: NiChartHarmonize
Version: 2.2.0
Summary: Harmonization tools for multi-center neuroimaging studies.
Home-page: https://github.com/rpomponiohttps://github.com/gurayerus/NiChartHarmonize
Author: Guray Erus
Author-email: guray.erus@pennmedicine.upenn.edu
License: MIT
License-File: LICENSE
Requires-Dist: numpy
Requires-Dist: pandas
Requires-Dist: nibabel
Requires-Dist: statsmodels >=0.12.0
